pymsl/__init__.py
pymsl/client.py
pymsl/exceptions.py
pymsl/utils.py
pymsl-1.2.dist-info/METADATA
pymsl-1.2.dist-info/RECORD
pymsl-1.2.dist-info/WHEEL
pymsl-1.2.dist-info/top_level.txt
