Metadata-Version: 2.1
Name: pymsl
Version: 1.2
Summary: Python library for interacting with the Netflix MSL API
Home-page: https://github.com/truedread/pymsl
Author: truedread
Author-email: truedread11@gmail.com
License: GNU GPLv3
Platform: UNKNOWN
Classifier: Environment :: Console
Classifier: License :: OSI Approved :: GNU General Public License v3 (GPLv3)
Classifier: Operating System :: OS Independent
Classifier: Programming Language :: Python :: 3.3
Classifier: Programming Language :: Python :: 3.4
Classifier: Programming Language :: Python :: 3.5
Classifier: Programming Language :: Python :: 3.6
Classifier: Programming Language :: Python :: 3.7
Classifier: Topic :: Utilities
Requires-Dist: pycryptodomex
Requires-Dist: requests
